optician/__main__.py
optician/cli/__init__.py
optician/cli/commands.py
optician/db_client/__init__.py
optician/db_client/db_client.py
optician/diff_tracker/__init__.py
optician/diff_tracker/diff_tracker.py
optician/logger.py
optician/lookml_generator/__init__.py
optician/lookml_generator/lookml_generator.py
optician/vc_client/__init__.py
optician/vc_client/vc_client.py
optician-1.1.1.dist-info/LICENSE
optician-1.1.1.dist-info/METADATA
optician-1.1.1.dist-info/WHEEL
optician-1.1.1.dist-info/entry_points.txt
optician-1.1.1.dist-info/RECORD
