Metadata-Version: 2.1
Name: optician
Version: 1.1.1
Summary: Sync your data warehouse tables to Looker
Home-page: https://github.com/getground/optician
License: MIT
Keywords: optician,looker,sync,lookml,dbt,data warehouse
Author: GetGround
Author-email: bi@getground.co.uk
Requires-Python: >=3.9,<4.0
Classifier: Development Status :: 4 - Beta
Classifier: License :: OSI Approved :: MIT License
Classifier: Programming Language :: Python
Classifier: Programming Language :: Python :: 3
Classifier: Programming Language :: Python :: 3.9
Classifier: Programming Language :: Python :: 3.10
Classifier: Programming Language :: Python :: 3.11
Classifier: Programming Language :: Python :: 3.12
Classifier: Topic :: Database
Classifier: Topic :: Software Development :: Libraries :: Python Modules
Provides-Extra: bigquery
Provides-Extra: postgres
Provides-Extra: redshift
Provides-Extra: snowflake
Requires-Dist: PyGithub (>=2.3.0,<3.0.0)
Requires-Dist: google-cloud-bigquery (>=3.10.0,<4.0.0) ; extra == "bigquery"
Requires-Dist: psycopg2 (>=2.9.9,<3.0.0) ; extra == "redshift" or extra == "postgres"
Requires-Dist: snowflake-connector-python (>=3.8.1,<4.0.0) ; extra == "snowflake"
Project-URL: Repository, https://github.com/getground/optician
